SQLAlchemyEasyConnection/DatabaseTypes.py
SQLAlchemyEasyConnection/EasyConnections.py
SQLAlchemyEasyConnection/Utilities.py
SQLAlchemyEasyConnection/__init__.py
test/__init__.py
test/test_Utilities.py
SQLAlchemy_Easy_Connection_0.0.2-0.0.2.dist-info/METADATA
SQLAlchemy_Easy_Connection_0.0.2-0.0.2.dist-info/WHEEL
SQLAlchemy_Easy_Connection_0.0.2-0.0.2.dist-info/top_level.txt
SQLAlchemy_Easy_Connection_0.0.2-0.0.2.dist-info/RECORD
